reindent.py
reindent-3.5.1.data/scripts/reindent
reindent-3.5.1.dist-info/METADATA
reindent-3.5.1.dist-info/WHEEL
reindent-3.5.1.dist-info/top_level.txt
reindent-3.5.1.dist-info/RECORD
