Metadata-Version: 2.1
Name: reindent
Version: 3.5.1
Summary: reindent script by Tim Peters
Home-page: UNKNOWN
Author: Tim Peters
Author-email: nottimsemail@notadomain.foo
Maintainer: Ryan Ollos
Maintainer-email: ryan.j.ollos@gmail.com
License: Public Domain
Keywords: reindent,pep8,syntax,lint,tab,space
Platform: any
Classifier: Development Status :: 6 - Mature
Classifier: Environment :: Console
Classifier: Intended Audience :: Developers
Classifier: License :: Public Domain
Classifier: Natural Language :: English
Classifier: Programming Language :: Python
Classifier: Programming Language :: Python :: 3
Classifier: Topic :: Software Development :: Quality Assurance
